README.rst
dimana/__init__.py
dimana/_exc.py
dimana/_typecheck.py
dimana/_units.py
dimana/_value.py
dimana/tests/__init__.py
dimana/tests/test_docstrings.py
dimana/tests/test_typecheck.py
dimana/tests/test_units.py
dimana/tests/test_value.py
dimana/tests/util.py
dimana-0.2.1.dist-info/DESCRIPTION.rst
dimana-0.2.1.dist-info/METADATA
dimana-0.2.1.dist-info/RECORD
dimana-0.2.1.dist-info/WHEEL
dimana-0.2.1.dist-info/metadata.json
dimana-0.2.1.dist-info/top_level.txt
