Metadata-Version: 2.0
Name: dimana
Version: 0.2.1
Summary: Dimensional Analysis - arithmetic with measurement units.
Home-page: https://github.org/nejucomo/dimana
Author: Nathan Wilcox
Author-email: nejucomo@gmail.com
License: TGPPLv1.0
Platform: UNKNOWN
